README.md
setup.py
L8module/MCm.py
L8module.egg-info/PKG-INFO
L8module.egg-info/SOURCES.txt
L8module.egg-info/dependency_links.txt
L8module.egg-info/requires.txt
L8module.egg-info/top_level.txt