Metadata-Version: 2.1
Name: L8module
Version: 0.1
Summary: A module for stock market simulation
Home-page: https://github.com/AgostinoCelora/L8module
Author: Agostino Celora
Author-email: celora.ago@gmail.com
